Workbook

Sheet Financial Statements
A1: Financial Metric | B1: 2023 | C1: 2024 | D1: 2025
A2: KRW million
A3: Revenue | B3: 33745470 | C3: 25619585 | D3: 23671759
A4: Operating Profit | B4: 2163234 | C4: 575387 | D4: 1346120
A5: Profit for the year (Consolidated) | B5: 1637985 | C5: 338602 | D5: 80803
A6: Cash & Cash Equivalents | B6: 5068783 | C6: 3898711 | D6: 3779307
A7: Current Borrowings | B7: 3211456 | C7: 2490240 | D7: 6686206
A8: Non-Current Borrowings | B8: 7720832 | C8: 12900311 | D8: 15825890
A9: Total Borrowings | B9: =B7+B8 -> 10932288 | C9: =C7+C8 -> 15390551 | D9: =D7+D8 -> 22512096
A10: Total Assets | B10: 45437144 | C10: 60306791 | D10: 67147953
A11: Total Liabilities | B11: 21063635 | C11: 29340248 | D11: 37826277
A12: Total Equity | B12: 24373509 | C12: 30966543 | D12: 29321676
A13: Operating Cash Flow | B13: 4444179 | C13: 5111700 | D13: 4432277
A14: Capital Expenditure (PPE) | B14: 9923051 | C14: 12399017 | D14: 10833917

Sheet Financial Ratios
A1: Financial Ratio | B1: 2023 | C1: 2024 | D1: 2025
A2: Revenue Growth | B2: N/A | C2: =('Financial Statements'!C3/'Financial Statements'!B3)-1 -> -0.24079928 | D2: =('Financial Statements'!D3/'Financial Statements'!C3)-1 -> -0.076028788
A3: Operating Profit Margin | B3: ='Financial Statements'!B4/'Financial Statements'!B3 -> 0.064104426 | C3: ='Financial Statements'!C4/'Financial Statements'!C3 -> 0.022458873 | D3: ='Financial Statements'!D4/'Financial Statements'!D3 -> 0.056866074
A4: Net Profit Margin | B4: ='Financial Statements'!B5/'Financial Statements'!B3 -> 0.048539404 | C4: ='Financial Statements'!C5/'Financial Statements'!C3 -> 0.013216529 | D4: ='Financial Statements'!D5/'Financial Statements'!D3 -> 0.0034134768
A5: Operating Cash Flow Margin | B5: ='Financial Statements'!B13/'Financial Statements'!B3 -> 0.13169705 | C5: ='Financial Statements'!C13/'Financial Statements'!C3 -> 0.19952314 | D5: ='Financial Statements'!D13/'Financial Statements'!D3 -> 0.18723902
A6: Debt-to-Equity | B6: ='Financial Statements'!B9/'Financial Statements'!B12 -> 0.44853156 | C6: ='Financial Statements'!C9/'Financial Statements'!C12 -> 0.49700578 | D6: ='Financial Statements'!D9/'Financial Statements'!D12 -> 0.76776293
A7: Cash / Current Borrowings | B7: ='Financial Statements'!B6/'Financial Statements'!B7 -> 1.5783442 | C7: ='Financial Statements'!C6/'Financial Statements'!C7 -> 1.5655965 | D7: ='Financial Statements'!D6/'Financial Statements'!D7 -> 0.56523939
A8: Liabilities / Assets | B8: ='Financial Statements'!B11/'Financial Statements'!B10 -> 0.46357744 | C8: ='Financial Statements'!C11/'Financial Statements'!C10 -> 0.48651649 | D8: ='Financial Statements'!D11/'Financial Statements'!D10 -> 0.56332733
A9: Net Debt (KRW million) | B9: ='Financial Statements'!B9-'Financial Statements'!B6 -> 5863505 | C9: ='Financial Statements'!C9-'Financial Statements'!C6 -> 11491840 | D9: ='Financial Statements'!D9-'Financial Statements'!D6 -> 18732789
A10: Free Cash Flow (PPE-only) | B10: ='Financial Statements'!B13-'Financial Statements'!B14 -> -5478872 | C10: ='Financial Statements'!C13-'Financial Statements'!C14 -> -7287317 | D10: ='Financial Statements'!D13-'Financial Statements'!D14 -> -6401640
A11: Free Cash Flow Margin | B11: =B10/'Financial Statements'!B3 -> -0.16235874 | C11: =C10/'Financial Statements'!C3 -> -0.28444321 | D11: =D10/'Financial Statements'!D3 -> -0.27043364
A12: Net Debt-to-Equity | B12: =B9/'Financial Statements'!B12 -> 0.24056877 | C12: =C9/'Financial Statements'!C12 -> 0.37110503 | D12: =D9/'Financial Statements'!D12 -> 0.6388717

Sheet Credit Analysis
A1: Credit Metric | B1: 2023 | C1: 2024 | D1: 2025
A2: KRW million, except ratios (x)
A3: Operating Profit (EBIT proxy) | B3: ='Financial Statements'!B4 -> 2163234 | C3: ='Financial Statements'!C4 -> 575387 | D3: ='Financial Statements'!D4 -> 1346120
A4: Depreciation | B4: 2150207 | C4: 2856045 | D4: 3413557
A5: Amortisation | B5: 136672 | C5: 189739 | D5: 277693
A6: EBITDA | B6: =SUM(B3:B5) -> 4450113 | C6: =SUM(C3:C5) -> 3621171 | D6: =SUM(D3:D5) -> 5037370
A7: Interest Expense | B7: 315752 | C7: 564246 | D7: 817154
A8: Interest Coverage (EBIT / Interest) | B8: =B3/B7 -> 6.851054 | C8: =C3/C7 -> 1.0197449 | D8: =D3/D7 -> 1.6473272
A9: EBITDA / Interest Expense | B9: =B6/B7 -> 14.093697 | C9: =C6/C7 -> 6.4177167 | D9: =D6/D7 -> 6.1645296
A10: Net Debt | B10: ='Financial Ratios'!B9 -> 5863505 | C10: ='Financial Ratios'!C9 -> 11491840 | D10: ='Financial Ratios'!D9 -> 18732789
A11: Net Debt / EBITDA | B11: =B10/B6 -> 1.3176081 | C11: =C10/C6 -> 3.1735149 | D11: =D10/D6 -> 3.7187638
A12: Total Borrowings | B12: ='Financial Statements'!B9 -> 10932288 | C12: ='Financial Statements'!C9 -> 15390551 | D12: ='Financial Statements'!D9 -> 22512096
A13: Operating Cash Flow | B13: ='Financial Statements'!B13 -> 4444179 | C13: ='Financial Statements'!C13 -> 5111700 | D13: ='Financial Statements'!D13 -> 4432277
A14: Borrowings / Operating Cash Flow | B14: =B12/B13 -> 2.4599117 | C14: =C12/C13 -> 3.0108479 | D14: =D12/D13 -> 5.0791266
A15: Current Assets | B15: 17208396 | C15: 15327395 | D15: 18412127
A16: Current Liabilities | B16: 10937185 | C16: 12054922 | D16: 16785357
A17: Current Ratio | B17: =B15/B16 -> 1.5733844 | C17: =C15/C16 -> 1.2714636 | D17: =D15/D16 -> 1.096916
A18: Cash / Current Borrowings | B18: ='Financial Ratios'!B7 -> 1.5783442 | C18: ='Financial Ratios'!C7 -> 1.5655965 | D18: ='Financial Ratios'!D7 -> 0.56523939

Sheet Scenario Analysis
A1: Financial Metric | B1: 2025 Actual | C1: 2026 Base | D1: 2026 Downside
A2: KRW million, except % and ratios
A3: Revenue Growth | B3: ='Financial Ratios'!D2 -> -0.076028788 | C3: -0.02 | D3: -0.1
A4: Revenue | B4: ='Financial Statements'!D3 -> 23671759 | C4: =$B$4*(1+C3) -> 23198324 | D4: =$B$4*(1+D3) -> 21304583
A5: Operating Profit Margin | B5: ='Financial Ratios'!D3 -> 0.056866074 | C5: 0.055 | D5: 0.03
A6: Operating Profit | B6: ='Financial Statements'!D4 -> 1346120 | C6: =C4*C5 -> 1275907.8 | D6: =D4*D5 -> 639137.49
A7: Depreciation & Amortisation | B7: ='Credit Analysis'!D4+'Credit Analysis'!D5 -> 3691250 | C7: =$B$7 -> 3691250 | D7: =$B$7 -> 3691250
A8: EBITDA (proxy) | B8: ='Credit Analysis'!D6 -> 5037370 | C8: =C6+C7 -> 4967157.8 | D8: =D6+D7 -> 4330387.5
A9: Operating Cash Flow Margin | B9: ='Financial Ratios'!D5 -> 0.18723902 | C9: 0.18 | D9: 0.13
A10: Operating Cash Flow | B10: ='Financial Statements'!D13 -> 4432277 | C10: =C4*C9 -> 4175698.3 | D10: =D4*D9 -> 2769595.8
A11: PPE CapEx (cash outflow) | B11: ='Financial Statements'!D14 -> 10833917 | C11: 9000000 | D11: 8500000
A12: Free Cash Flow (PPE-only) | B12: ='Financial Ratios'!D10 -> -6401640 | C12: =C10-C11 -> -4824301.7 | D12: =D10-D11 -> -5730404.2
A13: Net Debt (simplified) | B13: ='Financial Ratios'!D9 -> 18732789 | C13: =$B$13-C12 -> 23557091 | D13: =$B$13-D12 -> 24463193
A14: Net Debt / EBITDA | B14: ='Credit Analysis'!D11 -> 3.7187638 | C14: =C13/C8 -> 4.7425694 | D14: =D13/D8 -> 5.6491926
A15: Incremental Funding Rate | B15: N/A | C15: 0.05 | D15: 0.07
A16: Interest Expense (proxy) | B16: ='Credit Analysis'!D7 -> 817154 | C16: =$B$16+MAX(0,C13-$B$13)*C15/2 -> 937761.54 | D16: =$B$16+MAX(0,D13-$B$13)*D15/2 -> 1017718.1
A17: Interest Coverage | B17: ='Credit Analysis'!D8 -> 1.6473272 | C17: =C6/C16 -> 1.3605888 | D17: =D6/D16 -> 0.62801031
A20: Sensitivity Analysis—Net Debt/EBITDA
A22: Operating Margin/Revenue Growth | B22: -0.1 | C22: -0.06 | D22: -0.02 | E22: 0.02 | F22: 0.06
A23: 0.03 | B23: =($B$13-($B$4*(1+B$22)*$C$9-$C$11))/($B$4*(1+B$22)*$A23+$B$7) -> 5.5186664 | C23: =($B$13-($B$4*(1+C$22)*$C$9-$C$11))/($B$4*(1+C$22)*$A23+$B$7) -> 5.4435997 | D23: =($B$13-($B$4*(1+D$22)*$C$9-$C$11))/($B$4*(1+D$22)*$A23+$B$7) -> 5.369505 | E23: =($B$13-($B$4*(1+E$22)*$C$9-$C$11))/($B$4*(1+E$22)*$A23+$B$7) -> 5.2963636 | F23: =($B$13-($B$4*(1+F$22)*$C$9-$C$11))/($B$4*(1+F$22)*$A23+$B$7) -> 5.2241573
A24: 0.04 | B24: =($B$13-($B$4*(1+B$22)*$C$9-$C$11))/($B$4*(1+B$22)*$A24+$B$7) -> 5.259891 | C24: =($B$13-($B$4*(1+C$22)*$C$9-$C$11))/($B$4*(1+C$22)*$A24+$B$7) -> 5.1792036 | D24: =($B$13-($B$4*(1+D$22)*$C$9-$C$11))/($B$4*(1+D$22)*$A24+$B$7) -> 5.0998393 | E24: =($B$13-($B$4*(1+E$22)*$C$9-$C$11))/($B$4*(1+E$22)*$A24+$B$7) -> 5.0217659 | F24: =($B$13-($B$4*(1+F$22)*$C$9-$C$11))/($B$4*(1+F$22)*$A24+$B$7) -> 4.9449522
A25: 0.055 | B25: =($B$13-($B$4*(1+B$22)*$C$9-$C$11))/($B$4*(1+B$22)*$A25+$B$7) -> 4.914241 | C25: =($B$13-($B$4*(1+C$22)*$C$9-$C$11))/($B$4*(1+C$22)*$A25+$B$7) -> 4.8274957 | D25: =($B$13-($B$4*(1+D$22)*$C$9-$C$11))/($B$4*(1+D$22)*$A25+$B$7) -> 4.7425694 | E25: =($B$13-($B$4*(1+E$22)*$C$9-$C$11))/($B$4*(1+E$22)*$A25+$B$7) -> 4.6594054 | F25: =($B$13-($B$4*(1+F$22)*$C$9-$C$11))/($B$4*(1+F$22)*$A25+$B$7) -> 4.5779495
A26: 0.07 | B26: =($B$13-($B$4*(1+B$22)*$C$9-$C$11))/($B$4*(1+B$22)*$A26+$B$7) -> 4.611218 | C26: =($B$13-($B$4*(1+C$22)*$C$9-$C$11))/($B$4*(1+C$22)*$A26+$B$7) -> 4.5205177 | D26: =($B$13-($B$4*(1+D$22)*$C$9-$C$11))/($B$4*(1+D$22)*$A26+$B$7) -> 4.4320795 | E26: =($B$13-($B$4*(1+E$22)*$C$9-$C$11))/($B$4*(1+E$22)*$A26+$B$7) -> 4.3458199 | F26: =($B$13-($B$4*(1+F$22)*$C$9-$C$11))/($B$4*(1+F$22)*$A26+$B$7) -> 4.2616592
A27: 0.085 | B27: =($B$13-($B$4*(1+B$22)*$C$9-$C$11))/($B$4*(1+B$22)*$A27+$B$7) -> 4.3433947 | C27: =($B$13-($B$4*(1+C$22)*$C$9-$C$11))/($B$4*(1+C$22)*$A27+$B$7) -> 4.2502467 | D27: =($B$13-($B$4*(1+D$22)*$C$9-$C$11))/($B$4*(1+D$22)*$A27+$B$7) -> 4.1597463 | E27: =($B$13-($B$4*(1+E$22)*$C$9-$C$11))/($B$4*(1+E$22)*$A27+$B$7) -> 4.0717823 | F27: =($B$13-($B$4*(1+F$22)*$C$9-$C$11))/($B$4*(1+F$22)*$A27+$B$7) -> 3.9862494

Sheet Sources&Assumptions
A1: Sources & Assumptions
A3: Data Sources
A4: Data Category | B4: 2023 Data Source | C4: 2024 Data Source | D4: 2025 Data Source
A5: Income Statement | B5: 8 | C5: 9 | D5: 9
A6: Balance Sheet | B6: 7 | C6: 8 | D6: 8
A7: Cash Flow Statement | B7: 11 | C7: 12 | D7: 12
A8: Depreciation&Amortisation | B8: 2024 Report, 84 | C8: 2025 Report, 88 | D8: 88
A9: Interest Expense | B9: 2024 Report, 85 | C9: 2025 Report, 89 | D9: 89
A11: 2023 LGES Consolidated Audit Report | B11: https://www.lgensol.com/upload/file/audit-report/234Q_LGES_Audit_Report_CONFS_en.pdf
A12: 2024 LGES Consolidated Audit Report | B12: https://www.lgensol.com/upload/file/audit-report/2024_LGES_Audit_Report_Consolidated_FS_ENG.pdf
A13: 2025 LGES Consolidated Audit Report | B13: https://www.lgensol.com/upload/file/download/2025_LGES_Audit_Report_ConFS_ENG[0].pdf
A15: Financial Definitions & Methodology
A16: EBIT Proxy | B16: Reported operating profit from the consolidated income statement.
A17: EBITDA | B17: Operating profit + Depreciation + Amortisation. An analytical proxy, not a company-reported adjusted EBITDA.
A18: Interest Coverage | B18: Operating profit / Reported interest expense.
A19: Net Debt | B19: Current and non-current borrowings less cash and cash equivalents.
A20: Free Cash Flow | B20: Operating cash flow less acquisition of property, plant and equipment (PPE-only CapEx).
A21: Debt-to-Equity | B21: Total borrowings / Total equity.
A22: Current Ratio | B22: Current assets / Current liabilities.
A24: Data Notes
A25: 2024 interest expense | B25: KRW 564,246 million is taken from the 2025 audit report's comparative figures, compared with KRW 564,200 million in the original 2024 report. The KRW 46 million difference has not been independently reconciled.
A26: 2025 current assets | B26: It includes KRW 3,911,334 million of assets held for sale, which should be considered when interpreting the current ratio.
A27: Reporting Basis | B27: All financial data are consolidated and presented in KRW million unless otherwise stated.
A29: Scenario Assumptions & Limitations | B29: Illustrative 2026 scenarios based on FY2025 audited financial statements, not company guidance. Base and downside assumptions are hypothetical. Depreciation and amortisation are held constant at FY2025 levels. Negative free cash flow is assumed to be debt-funded, with additional interest estimated using average incremental financing. The model excludes dividends, asset disposals, FX adjustments and the feedback of additional interest costs into operating cash flow. Interim 2026 financial results are not incorporated.
